{
    "type": "minecraft:stonecutting",
    "ingredient": "minecraft:carved_pumpkin",
    "result": {
        "id": "minecraft:player_head",
        "count": 4,
        "components": {
            "minecraft:rarity": "uncommon",
            "minecraft:note_block_sound": "minecraft:entity.parrot.imitate.shulker",
            "minecraft:custom_name": "{\"fallback\":\"Carved Shulker Pumpkin\",\"translate\":\"miniblock.eden.carved_shulker_pumpkin\",\"italic\":false}",
            "minecraft:profile": {
                "properties": [
                    {
                        "name": "textures",
                        "value": "eyJ0ZXh0dXJlcyI6eyJTS0lOIjp7InVybCI6Imh0dHA6Ly90ZXh0dXJlcy5taW5lY3JhZnQubmV0L3RleHR1cmUvYTQxYzE1MGJkMzExNTk1MzQyNTJlNTQzNWNkMjUwYzExMTA4NDg4NDI0ZDA5Y2Y1ZmE2ZTRiYTM1MGViNDY3ZiJ9fX0="
                    }
                ]
            }
        }
    }
}