{
    "pools": [
      {
        "rolls": 1,
        "entries": [
          {
            "type": "minecraft:loot_table",
            "value": "eden:item/equipment/aetherian_leggings"
          },
          {
            "type": "minecraft:loot_table",
            "value": "eden:item/equipment/angels_leggings"
          },
          {
            "type": "minecraft:loot_table",
            "value": "eden:item/equipment/armadillo_leggings"
          },
          {
            "type": "minecraft:loot_table",
            "value": "eden:item/equipment/centurion_leggings"
          },
          {
            "type": "minecraft:loot_table",
            "value": "eden:item/equipment/copper_leggings"
          },
          {
            "type": "minecraft:loot_table",
            "value": "eden:item/equipment/cottage_leggings"
          },
          {
            "type": "minecraft:loot_table",
            "value": "eden:item/equipment/crystal_leggings"
          },
          {
            "type": "minecraft:loot_table",
            "value": "eden:item/equipment/devils_leggings"
          },
          {
            "type": "minecraft:loot_table",
            "value": "eden:item/equipment/fox_leggings"
          },
          {
            "type": "minecraft:loot_table",
            "value": "eden:item/equipment/legionnaries_leggings"
          },
          {
            "type": "minecraft:loot_table",
            "value": "eden:item/equipment/melon_leggings"
          },
          {
            "type": "minecraft:loot_table",
            "value": "eden:item/equipment/pillager_leggings"
          },
          {
            "type": "minecraft:loot_table",
            "value": "eden:item/equipment/sakura_leggings"
          },
          {
            "type": "minecraft:loot_table",
            "value": "eden:item/equipment/skater_leggings"
          },
          {
            "type": "minecraft:loot_table",
            "value": "eden:item/equipment/techno_tribute_leggings"
          },
          {
            "type": "minecraft:loot_table",
            "value": "eden:item/equipment/turtle_leggings"
          },
          {
            "type": "minecraft:loot_table",
            "value": "eden:item/equipment/warden_leggings"
          },
          {
            "type": "minecraft:loot_table",
            "value": "eden:item/equipment/aquanaut_leggings"
          },
          {
            "type": "minecraft:loot_table",
            "value": "eden:item/equipment/black_berserk_leggings"
          },
          {
            "type": "minecraft:loot_table",
            "value": "eden:item/equipment/black_daimyo_leggings"
          },
          {
            "type": "minecraft:loot_table",
            "value": "eden:item/equipment/black_ronin_leggings"
          },
          {
            "type": "minecraft:loot_table",
            "value": "eden:item/equipment/black_samurai_leggings"
          },
          {
            "type": "minecraft:loot_table",
            "value": "eden:item/equipment/blue_samurai_leggings"
          },
          {
            "type": "minecraft:loot_table",
            "value": "eden:item/equipment/brown_berserk_leggings"
          },
          {
            "type": "minecraft:loot_table",
            "value": "eden:item/equipment/brown_daimyo_leggings"
          },
          {
            "type": "minecraft:loot_table",
            "value": "eden:item/equipment/brown_ronin_leggings"
          },
          {
            "type": "minecraft:loot_table",
            "value": "eden:item/equipment/brown_samurai_leggings"
          },
          {
            "type": "minecraft:loot_table",
            "value": "eden:item/equipment/ceasar_leggings"
          },
          {
            "type": "minecraft:loot_table",
            "value": "eden:item/equipment/climber_leggings"
          },
          {
            "type": "minecraft:loot_table",
            "value": "eden:item/equipment/doctor_leggings"
          },
          {
            "type": "minecraft:loot_table",
            "value": "eden:item/equipment/emperor_leggings"
          },
          {
            "type": "minecraft:loot_table",
            "value": "eden:item/equipment/firebender_leggings"
          },
          {
            "type": "minecraft:loot_table",
            "value": "eden:item/equipment/flower_leggings"
          },
          {
            "type": "minecraft:loot_table",
            "value": "eden:item/equipment/gladiator_leggings"
          },
          {
            "type": "minecraft:loot_table",
            "value": "eden:item/equipment/golden_viking_leggings"
          },
          {
            "type": "minecraft:loot_table",
            "value": "eden:item/equipment/gray_berserk_leggings"
          },
          {
            "type": "minecraft:loot_table",
            "value": "eden:item/equipment/green_daimyo_leggings"
          },
          {
            "type": "minecraft:loot_table",
            "value": "eden:item/equipment/guardian_leggings"
          },
          {
            "type": "minecraft:loot_table",
            "value": "eden:item/equipment/hermes_leggings"
          },
          {
            "type": "minecraft:loot_table",
            "value": "eden:item/equipment/hoplite_leggings"
          },
          {
            "type": "minecraft:loot_table",
            "value": "eden:item/equipment/hunter_leggings"
          },
          {
            "type": "minecraft:loot_table",
            "value": "eden:item/equipment/iron_viking_leggings"
          },
          {
            "type": "minecraft:loot_table",
            "value": "eden:item/equipment/jarl_leggings"
          },
          {
            "type": "minecraft:loot_table",
            "value": "eden:item/equipment/legate_leggings"
          },
          {
            "type": "minecraft:loot_table",
            "value": "eden:item/equipment/magnate_leggings"
          },
          {
            "type": "minecraft:loot_table",
            "value": "eden:item/equipment/merchant_leggings"
          },
          {
            "type": "minecraft:loot_table",
            "value": "eden:item/equipment/night_king_leggings"
          },
          {
            "type": "minecraft:loot_table",
            "value": "eden:item/equipment/olympus_leggings"
          },
          {
            "type": "minecraft:loot_table",
            "value": "eden:item/equipment/pharaoh_leggings"
          },
          {
            "type": "minecraft:loot_table",
            "value": "eden:item/equipment/psiloi_leggings"
          },
          {
            "type": "minecraft:loot_table",
            "value": "eden:item/equipment/raider_leggings"
          },
          {
            "type": "minecraft:loot_table",
            "value": "eden:item/equipment/red_daimyo_leggings"
          },
          {
            "type": "minecraft:loot_table",
            "value": "eden:item/equipment/red_samurai_leggings"
          },
          {
            "type": "minecraft:loot_table",
            "value": "eden:item/equipment/remus_leggings"
          },
          {
            "type": "minecraft:loot_table",
            "value": "eden:item/equipment/romulus_leggings"
          },
          {
            "type": "minecraft:loot_table",
            "value": "eden:item/equipment/senator_leggings"
          },
          {
            "type": "minecraft:loot_table",
            "value": "eden:item/equipment/snow_fox_leggings"
          },
          {
            "type": "minecraft:loot_table",
            "value": "eden:item/equipment/studded_viking_leggings"
          },
          {
            "type": "minecraft:loot_table",
            "value": "eden:item/equipment/thor_leggings"
          },
          {
            "type": "minecraft:loot_table",
            "value": "eden:item/equipment/undead_wolf_leggings"
          },
          {
            "type": "minecraft:loot_table",
            "value": "eden:item/equipment/wasteland_leggings"
          },
          {
            "type": "minecraft:loot_table",
            "value": "eden:item/equipment/white_daimyo_leggings"
          },
          {
            "type": "minecraft:loot_table",
            "value": "eden:item/equipment/white_samurai_leggings"
          },
          {
            "type": "minecraft:loot_table",
            "value": "eden:item/equipment/winter_guard_leggings"
          },
          {
            "type": "minecraft:loot_table",
            "value": "eden:item/equipment/wizard_leggings"
          },
          {
            "type": "minecraft:loot_table",
            "value": "eden:item/equipment/woodland_leggings"
          }
        ]
      }
    ]
  }
  