{
    "name": "astral_plane:blackstone_fort/main_decor",
    "fallback": "minecraft:empty",
	"elements": [
		{
			"weight": 1,
			"element": {
				"element_type": "minecraft:single_pool_element",
				"projection": "rigid",
				"location": "astral_plane:blackstone_fort/main_decor_1",
				"override_liquid_settings": "apply_waterlogging",
				"processors": "minecraft:empty"
			}
		},
		{
			"weight": 1,
			"element": {
				"element_type": "minecraft:single_pool_element",
				"projection": "rigid",
				"location": "astral_plane:blackstone_fort/main_decor_2",
				"override_liquid_settings": "apply_waterlogging",
				"processors": "minecraft:empty"
			}
		},
		{
			"weight": 1,
			"element": {
				"element_type": "minecraft:single_pool_element",
				"projection": "rigid",
				"location": "astral_plane:blackstone_fort/main_decor_3",
				"override_liquid_settings": "apply_waterlogging",
				"processors": "minecraft:empty"
			}
		},
		{
			"weight": 1,
			"element": {
				"element_type": "minecraft:single_pool_element",
				"projection": "rigid",
				"location": "astral_plane:blackstone_fort/main_decor_4",
				"override_liquid_settings": "apply_waterlogging",
				"processors": "minecraft:empty"
			}
		},
		{
			"weight": 1,
			"element": {
				"element_type": "minecraft:single_pool_element",
				"projection": "rigid",
				"location": "astral_plane:blackstone_fort/main_decor_5",
				"override_liquid_settings": "apply_waterlogging",
				"processors": "minecraft:empty"
			}
		},
		{
			"weight": 1,
			"element": {
				"element_type": "minecraft:single_pool_element",
				"projection": "rigid",
				"location": "astral_plane:blackstone_fort/main_decor_6",
				"override_liquid_settings": "apply_waterlogging",
				"processors": "minecraft:empty"
			}
		},
		{
			"weight": 1,
			"element": {
				"element_type": "minecraft:single_pool_element",
				"projection": "rigid",
				"location": "astral_plane:blackstone_fort/main_decor_7",
				"override_liquid_settings": "apply_waterlogging",
				"processors": "minecraft:empty"
			}
		},
		{
			"weight": 1,
			"element": {
				"element_type": "minecraft:single_pool_element",
				"projection": "rigid",
				"location": "astral_plane:blackstone_fort/main_decor_8",
				"override_liquid_settings": "apply_waterlogging",
				"processors": "minecraft:empty"
			}
		},
		{
			"weight": 1,
			"element": {
				"element_type": "minecraft:single_pool_element",
				"projection": "rigid",
				"location": "astral_plane:blackstone_fort/main_decor_9",
				"override_liquid_settings": "apply_waterlogging",
				"processors": "minecraft:empty"
			}
		},
		{
			"weight": 1,
			"element": {
				"element_type": "minecraft:single_pool_element",
				"projection": "rigid",
				"location": "astral_plane:blackstone_fort/main_decor_10",
				"override_liquid_settings": "apply_waterlogging",
				"processors": "minecraft:empty"
			}
		},
		{
			"weight": 1,
			"element": {
				"element_type": "minecraft:single_pool_element",
				"projection": "rigid",
				"location": "astral_plane:blackstone_fort/main_decor_11",
				"override_liquid_settings": "apply_waterlogging",
				"processors": "minecraft:empty"
			}
		},
		{
			"weight": 1,
			"element": {
				"element_type": "minecraft:single_pool_element",
				"projection": "rigid",
				"location": "astral_plane:blackstone_fort/main_decor_12",
				"override_liquid_settings": "apply_waterlogging",
				"processors": "minecraft:empty"
			}
		},
		{
			"weight": 1,
			"element": {
				"element_type": "minecraft:single_pool_element",
				"projection": "rigid",
				"location": "astral_plane:blackstone_fort/main_decor_13",
				"override_liquid_settings": "apply_waterlogging",
				"processors": "minecraft:empty"
			}
		},
		{
			"weight": 1,
			"element": {
				"element_type": "minecraft:single_pool_element",
				"projection": "rigid",
				"location": "astral_plane:blackstone_fort/main_decor_14",
				"override_liquid_settings": "apply_waterlogging",
				"processors": "minecraft:empty"
			}
		},
		{
			"weight": 1,
			"element": {
				"element_type": "minecraft:single_pool_element",
				"projection": "rigid",
				"location": "astral_plane:blackstone_fort/main_decor_15",
				"override_liquid_settings": "apply_waterlogging",
				"processors": "minecraft:empty"
			}
		}
	]
}